rotary_encoder/__init__.py
rotary_encoder/_rotary_encoder.py
rotary_encoder/py.typed
rpi_rotary_encoder-0.2.0.dist-info/WHEEL
rpi_rotary_encoder-0.2.0.dist-info/METADATA
rpi_rotary_encoder-0.2.0.dist-info/RECORD
