Metadata-Version: 2.1
Name: rpi-rotary-encoder
Version: 0.2.0
Summary: A rotary encoder library for the raspberry pi that "just works"
License: MIT
Author: Momo Eissenhauer
Author-email: momo.eissenhauer@gmail.com
Requires-Python: >=3.9,<4.0
Classifier: License :: OSI Approved :: MIT License
Classifier: Programming Language :: Python :: 3
Classifier: Programming Language :: Python :: 3.9
Classifier: Programming Language :: Python :: 3.10
Classifier: Programming Language :: Python :: 3.11
Requires-Dist: rotary-encoder-gpio-core (>=0.1.0,<0.2.0)
